{
    "id": "emma-rowley",
    "name": "Emma Rowley",
    "title": "Senior UX Designer & Design Systems Lead",
    "bio": "Emma Rowley is a seasoned UX designer with over a decade of experience crafting digital experiences for Fortune 500 companies. She specializes in design systems, user research, and accessibility. Currently leading design system initiatives at major tech companies, Emma frequently speaks at design conferences and mentors emerging UX designers.",
    "image": "/images/authors/emma_rowley.jpeg",
    "socialLinks": {
        "linkedin": "https://www.linkedin.com/in/emma-rowley-ux",
        "twitter": "https://twitter.com/emmarowleyux",
        "instagram": "https://www.instagram.com/emmarowleydesign",
        "email": "emma.rowley@designsystems.io"
    }
} 